pymor/__init__.py
pymor/basic.py
pymor/algorithms/__init__.py
pymor/algorithms/adaptivegreedy.py
pymor/algorithms/basic.py
pymor/algorithms/bernoulli.py
pymor/algorithms/bfgs.py
pymor/algorithms/chol_qr.py
pymor/algorithms/dmd.py
pymor/algorithms/ei.py
pymor/algorithms/eigs.py
pymor/algorithms/error.py
pymor/algorithms/gram_schmidt.py
pymor/algorithms/greedy.py
pymor/algorithms/hapod.py
pymor/algorithms/image.py
pymor/algorithms/krylov.py
pymor/algorithms/lincomb.py
pymor/algorithms/line_search.py
pymor/algorithms/lradi.py
pymor/algorithms/lrradi.py
pymor/algorithms/lyapunov.py
pymor/algorithms/pod.py
pymor/algorithms/preassemble.py
pymor/algorithms/projection.py
pymor/algorithms/rand_la.py
pymor/algorithms/riccati.py
pymor/algorithms/rules.py
pymor/algorithms/samdp.py
pymor/algorithms/scm.py
pymor/algorithms/simplify.py
pymor/algorithms/svd_va.py
pymor/algorithms/sylvester.py
pymor/algorithms/symplectic.py
pymor/algorithms/timestepping.py
pymor/algorithms/to_matrix.py
pymor/algorithms/tr.py
pymor/algorithms/ml/__init__.py
pymor/algorithms/ml/nn/__init__.py
pymor/algorithms/ml/nn/neural_networks.py
pymor/algorithms/ml/nn/regressor.py
pymor/algorithms/ml/nn/train.py
pymor/algorithms/ml/nn/utils.py
pymor/algorithms/ml/vkoga/__init__.py
pymor/algorithms/ml/vkoga/kernels.py
pymor/algorithms/ml/vkoga/regressor.py
pymor/analyticalproblems/__init__.py
pymor/analyticalproblems/burgers.py
pymor/analyticalproblems/domaindescriptions.py
pymor/analyticalproblems/elliptic.py
pymor/analyticalproblems/expressions.py
pymor/analyticalproblems/functions.py
pymor/analyticalproblems/helmholtz.py
pymor/analyticalproblems/instationary.py
pymor/analyticalproblems/text.py
pymor/analyticalproblems/thermalblock.py
pymor/bindings/__init__.py
pymor/bindings/fenics.py
pymor/bindings/fenicsx.py
pymor/bindings/ngsolve.py
pymor/bindings/scipy.py
pymor/bindings/slycot.py
pymor/core/__init__.py
pymor/core/base.py
pymor/core/cache.py
pymor/core/config.py
pymor/core/defaults.py
pymor-2025.2.0.dist-info/METADATA
pymor-2025.2.0.dist-info/WHEEL
pymor-2025.2.0.dist-info/entry_points.txt
pymor-2025.2.0.dist-info/licenses/LICENSE.txt
pymor-2025.2.0.dist-info/licenses/LICENSES_bundled.txt
pymor-2025.2.0.dist-info/RECORD
