Metadata-Version: 2.4
Name: pymor
Version: 2025.2.0
Summary: Library for building model order reduction applications with Python
Project-URL: homepage, https://pymor.org
Project-URL: documentation, https://docs.pymor.org
Project-URL: source, https://github.com/pymor/pymor
Project-URL: tracker, https://github.com/pymor/pymor/issues
Project-URL: release notes, https://docs.pymor.org/latest/release_notes/all.html
Author-email: pyMOR developers <main.developers@pymor.org>
Maintainer-email: Stephan Rave <stephan.rave@uni-muenster.de>
License-Expression: BSD-2-Clause AND BSD-3-Clause
License-File: LICENSE.txt
License-File: LICENSES_bundled.txt
Classifier: Intended Audience :: Science/Research
Classifier: Programming Language :: Python :: 3.10
Classifier: Programming Language :: Python :: 3.11
Classifier: Programming Language :: Python :: 3.12
Classifier: Programming Language :: Python :: 3.13
Classifier: Topic :: Scientific/Engineering :: Mathematics
Requires-Python: >=3.10
Requires-Dist: diskcache
Requires-Dist: matplotlib>=3.5.0
Requires-Dist: numpy!=1.25.0,>=1.21
Requires-Dist: packaging
Requires-Dist: pillow
Requires-Dist: pygments
Requires-Dist: qtpy>=2.3.1
Requires-Dist: scipy!=1.15.0,!=1.15.1,!=1.15.2,>=1.8
Requires-Dist: threadpoolctl
Requires-Dist: typer
Provides-Extra: ann
Requires-Dist: torch>=1.11.0; extra == 'ann'
Provides-Extra: ci-conda
Requires-Dist: pyopengl!=3.1.10,!=3.1.7,!=3.1.9; extra == 'ci-conda'
Provides-Extra: dev
Requires-Dist: conda-lock==2.5.7; extra == 'dev'
Requires-Dist: hatch; extra == 'dev'
Requires-Dist: ruff==0.13.3; extra == 'dev'
Requires-Dist: uv; extra == 'dev'
Provides-Extra: docs
Requires-Dist: astroid<4; extra == 'docs'
Requires-Dist: bash-kernel; extra == 'docs'
Requires-Dist: docutils; extra == 'docs'
Requires-Dist: ipympl; extra == 'docs'
Requires-Dist: ipywidgets>7; extra == 'docs'
Requires-Dist: jupyterlab; extra == 'docs'
Requires-Dist: jupyterlab-myst; extra == 'docs'
Requires-Dist: k3d>=2.15.2; extra == 'docs'
Requires-Dist: myst-nb>=0.16; extra == 'docs'
Requires-Dist: notebook; extra == 'docs'
Requires-Dist: pybind11[global]; extra == 'docs'
Requires-Dist: python-slugify; extra == 'docs'
Requires-Dist: slycot>=0.5.4; extra == 'docs'
Requires-Dist: sphinx-autoapi==3.1.2; extra == 'docs'
Requires-Dist: sphinx-material; extra == 'docs'
Requires-Dist: sphinx==7.3.7; extra == 'docs'
Requires-Dist: sphinxcontrib-bibtex; extra == 'docs'
Requires-Dist: torch>=1.11.0; extra == 'docs'
Provides-Extra: docs-additional
Requires-Dist: astroid<4; extra == 'docs-additional'
Requires-Dist: bash-kernel; extra == 'docs-additional'
Requires-Dist: docutils; extra == 'docs-additional'
Requires-Dist: myst-nb>=0.16; extra == 'docs-additional'
Requires-Dist: pybind11[global]; extra == 'docs-additional'
Requires-Dist: python-slugify; extra == 'docs-additional'
Requires-Dist: sphinx-autoapi==3.1.2; extra == 'docs-additional'
Requires-Dist: sphinx-material; extra == 'docs-additional'
Requires-Dist: sphinx==7.3.7; extra == 'docs-additional'
Requires-Dist: sphinxcontrib-bibtex; extra == 'docs-additional'
Provides-Extra: full
Requires-Dist: astroid<4; extra == 'full'
Requires-Dist: bash-kernel; extra == 'full'
Requires-Dist: conda-lock==2.5.7; extra == 'full'
Requires-Dist: docutils; extra == 'full'
Requires-Dist: gmsh; extra == 'full'
Requires-Dist: hatch; extra == 'full'
Requires-Dist: hypothesis[numpy,pytest]==6.56.3; extra == 'full'
Requires-Dist: ipympl; extra == 'full'
Requires-Dist: ipyparallel>=6.2.5; extra == 'full'
Requires-Dist: ipywidgets>7; extra == 'full'
Requires-Dist: jupyterlab; extra == 'full'
Requires-Dist: jupyterlab-myst; extra == 'full'
Requires-Dist: k3d>=2.15.2; extra == 'full'
Requires-Dist: lxml; extra == 'full'
Requires-Dist: meshio>=4.4; extra == 'full'
Requires-Dist: myst-nb>=0.16; extra == 'full'
Requires-Dist: nbmake; extra == 'full'
Requires-Dist: ngsolve; extra == 'full'
Requires-Dist: notebook; extra == 'full'
Requires-Dist: pybind11[global]; extra == 'full'
Requires-Dist: pyevtk; extra == 'full'
Requires-Dist: pyopengl; extra == 'full'
Requires-Dist: pyside6>=6.4.3; extra == 'full'
Requires-Dist: pytest-cov; extra == 'full'
Requires-Dist: pytest-datadir; extra == 'full'
Requires-Dist: pytest>=7.2.1; extra == 'full'
Requires-Dist: python-slugify; extra == 'full'
Requires-Dist: ruff==0.13.3; extra == 'full'
Requires-Dist: scikit-fem>=6.0.0; extra == 'full'
Requires-Dist: sphinx-autoapi==3.1.2; extra == 'full'
Requires-Dist: sphinx-material; extra == 'full'
Requires-Dist: sphinx==7.3.7; extra == 'full'
Requires-Dist: sphinxcontrib-bibtex; extra == 'full'
Requires-Dist: torch>=1.11.0; extra == 'full'
Requires-Dist: uv; extra == 'full'
Requires-Dist: xmljson; extra == 'full'
Provides-Extra: full-compiled
Requires-Dist: astroid<4; extra == 'full-compiled'
Requires-Dist: bash-kernel; extra == 'full-compiled'
Requires-Dist: conda-lock==2.5.7; extra == 'full-compiled'
Requires-Dist: docutils; extra == 'full-compiled'
Requires-Dist: gmsh; extra == 'full-compiled'
Requires-Dist: hatch; extra == 'full-compiled'
Requires-Dist: hypothesis[numpy,pytest]==6.56.3; extra == 'full-compiled'
Requires-Dist: ipympl; extra == 'full-compiled'
Requires-Dist: ipyparallel>=6.2.5; extra == 'full-compiled'
Requires-Dist: ipywidgets>7; extra == 'full-compiled'
Requires-Dist: jupyterlab; extra == 'full-compiled'
Requires-Dist: jupyterlab-myst; extra == 'full-compiled'
Requires-Dist: k3d>=2.15.2; extra == 'full-compiled'
Requires-Dist: lxml; extra == 'full-compiled'
Requires-Dist: meshio>=4.4; extra == 'full-compiled'
Requires-Dist: mpi4py>=3.0.3; extra == 'full-compiled'
Requires-Dist: myst-nb>=0.16; extra == 'full-compiled'
Requires-Dist: nbmake; extra == 'full-compiled'
Requires-Dist: ngsolve; extra == 'full-compiled'
Requires-Dist: notebook; extra == 'full-compiled'
Requires-Dist: pybind11[global]; extra == 'full-compiled'
Requires-Dist: pyevtk; extra == 'full-compiled'
Requires-Dist: pyopengl; extra == 'full-compiled'
Requires-Dist: pyside6>=6.4.3; extra == 'full-compiled'
Requires-Dist: pytest-cov; extra == 'full-compiled'
Requires-Dist: pytest-datadir; extra == 'full-compiled'
Requires-Dist: pytest>=7.2.1; extra == 'full-compiled'
Requires-Dist: python-slugify; extra == 'full-compiled'
Requires-Dist: ruff==0.13.3; extra == 'full-compiled'
Requires-Dist: scikit-fem>=6.0.0; extra == 'full-compiled'
Requires-Dist: slycot>=0.5.4; extra == 'full-compiled'
Requires-Dist: sphinx-autoapi==3.1.2; extra == 'full-compiled'
Requires-Dist: sphinx-material; extra == 'full-compiled'
Requires-Dist: sphinx==7.3.7; extra == 'full-compiled'
Requires-Dist: sphinxcontrib-bibtex; extra == 'full-compiled'
Requires-Dist: torch>=1.11.0; extra == 'full-compiled'
Requires-Dist: uv; extra == 'full-compiled'
Requires-Dist: xmljson; extra == 'full-compiled'
Provides-Extra: gmsh
Requires-Dist: gmsh; extra == 'gmsh'
Provides-Extra: gui
Requires-Dist: pyopengl; extra == 'gui'
Requires-Dist: pyside6>=6.4.3; extra == 'gui'
Provides-Extra: ipyparallel
Requires-Dist: ipyparallel>=6.2.5; extra == 'ipyparallel'
Provides-Extra: jupyter
Requires-Dist: ipympl; extra == 'jupyter'
Requires-Dist: ipywidgets>7; extra == 'jupyter'
Requires-Dist: jupyterlab; extra == 'jupyter'
Requires-Dist: jupyterlab-myst; extra == 'jupyter'
Requires-Dist: k3d>=2.15.2; extra == 'jupyter'
Requires-Dist: notebook; extra == 'jupyter'
Provides-Extra: mpi
Requires-Dist: mpi4py>=3.0.3; extra == 'mpi'
Provides-Extra: ngsolve
Requires-Dist: ngsolve; extra == 'ngsolve'
Provides-Extra: scikit-fem
Requires-Dist: scikit-fem>=6.0.0; extra == 'scikit-fem'
Provides-Extra: scikit-learn
Requires-Dist: scikit-learn; extra == 'scikit-learn'
Provides-Extra: slycot
Requires-Dist: slycot>=0.5.4; extra == 'slycot'
Provides-Extra: tests
Requires-Dist: hypothesis[numpy,pytest]==6.56.3; extra == 'tests'
Requires-Dist: nbmake; extra == 'tests'
Requires-Dist: pytest-cov; extra == 'tests'
Requires-Dist: pytest-datadir; extra == 'tests'
Requires-Dist: pytest>=7.2.1; extra == 'tests'
Provides-Extra: vtk
Requires-Dist: lxml; extra == 'vtk'
Requires-Dist: meshio>=4.4; extra == 'vtk'
Requires-Dist: pyevtk; extra == 'vtk'
Requires-Dist: xmljson; extra == 'vtk'
